gen_random_str/__init__.py
gen_random_str/generate_string.py
generate_random_string-1.0.3.dist-info/LICENSE.txt
generate_random_string-1.0.3.dist-info/METADATA
generate_random_string-1.0.3.dist-info/WHEEL
generate_random_string-1.0.3.dist-info/top_level.txt
generate_random_string-1.0.3.dist-info/RECORD
