Metadata-Version: 2.1
Name: generate-random-string
Version: 1.0.3
Summary: A package generates a specify length random string,belongs:alphabet、nums or their mix
Home-page: 
Author: wuguipeng
Author-email: 734426750@qq.com
License: MIT License
Platform: all
Classifier: Intended Audience :: Developers
Classifier: Operating System :: OS Independent
Classifier: Natural Language :: Chinese (Simplified)
Classifier: Programming Language :: Python
Classifier: Programming Language :: Python :: 2
Classifier: Programming Language :: Python :: 3
Classifier: Topic :: Software Development :: Libraries
License-File: LICENSE.txt
